console_logging/__init__.py
console_logging/console.py
console_logging-0.0.5.0.dist-info/DESCRIPTION.rst
console_logging-0.0.5.0.dist-info/METADATA
console_logging-0.0.5.0.dist-info/RECORD
console_logging-0.0.5.0.dist-info/WHEEL
console_logging-0.0.5.0.dist-info/metadata.json
console_logging-0.0.5.0.dist-info/top_level.txt
